pytreexo.py
_pytreexo/bindings.py
_pytreexo/proof.py
_pytreexo/stump.py
pytreexo-0.1.1.dist-info/METADATA
pytreexo-0.1.1.dist-info/WHEEL
pytreexo-0.1.1.dist-info/top_level.txt
pytreexo-0.1.1.dist-info/zip-safe
pytreexo-0.1.1.dist-info/RECORD
